perftools/__init__.py
perftools/androidsdk.py
perftools/apkrepacker.py
perftools/executable.py
perftools/logger.py
perftools/perfdata.py
perftools/perfstats.py
perftools/simpleperf.py
perftools/bin/apktool.jar
perftools/bin/AndroidSdk/build-tools/34.0.0/zipalign
perftools/bin/AndroidSdk/build-tools/34.0.0/zipalign.exe
perftools/bin/AndroidSdk/build-tools/34.0.0/lib/apksigner.jar
perftools/bin/AndroidSdk/build-tools/34.0.0/lib64/libc++.so
perftools/bin/AndroidSdk/ndk/27.0.11902837/simpleperf/simpleperf_report_lib.py
perftools/bin/AndroidSdk/ndk/27.0.11902837/simpleperf/simpleperf_utils.py
perftools/bin/AndroidSdk/ndk/27.0.11902837/simpleperf/bin/android/arm/simpleperf
perftools/bin/AndroidSdk/ndk/27.0.11902837/simpleperf/bin/android/arm64/simpleperf
perftools/bin/AndroidSdk/ndk/27.0.11902837/simpleperf/bin/android/riscv64/simpleperf
perftools/bin/AndroidSdk/ndk/27.0.11902837/simpleperf/bin/android/x86/simpleperf
perftools/bin/AndroidSdk/ndk/27.0.11902837/simpleperf/bin/android/x86_64/simpleperf
perftools/bin/AndroidSdk/ndk/27.0.11902837/simpleperf/bin/linux/x86_64/libsimpleperf_report.so
perftools/bin/AndroidSdk/ndk/27.0.11902837/simpleperf/bin/linux/x86_64/simpleperf
perftools/bin/AndroidSdk/ndk/27.0.11902837/simpleperf/bin/windows/x86_64/libsimpleperf_report.dll
perftools/bin/AndroidSdk/ndk/27.0.11902837/simpleperf/bin/windows/x86_64/libwinpthread-1.dll
perftools/bin/AndroidSdk/ndk/27.0.11902837/simpleperf/bin/windows/x86_64/simpleperf.exe
perftools/bin/AndroidSdk/platform-tools/AdbWinApi.dll
perftools/bin/AndroidSdk/platform-tools/adb
perftools/bin/AndroidSdk/platform-tools/adb.exe
perftools/data/repack_default.keystore
perftools-0.2.5.dist-info/LICENSE
perftools-0.2.5.dist-info/METADATA
perftools-0.2.5.dist-info/WHEEL
perftools-0.2.5.dist-info/top_level.txt
perftools-0.2.5.dist-info/RECORD
